
    {
        "dataList":[
            {
                "id":0,
                "model":"싱클레어",
                "content":"Như một quy tắc trong gia đình, cả nhà tôi thường ăn sáng cùng nhau mỗi ngày.",
                "place":null,
                "teller":null,
                "title":null
            },
            {
                "id":1,
                "model":"싱클레어",
                "content":"Đó là một quãng thời gian hạnh phúc khi gia đình tôi ngồi lại quanh một cái bàn, sẽ chia những câu chuyện của bản thân và dành cho nhau những lời động viên hay những câu nói đùa.",
                "place":null,
                "teller":null,
                "title":null
            },
            {
                "id":2,
                "model":"싱클레어",
                "content":"Tôi yêu những buổi sáng ấy, và quy tắc ấy như một liều thuốc xoa dịu trái tim tôi vậy.",
                "place":null,
                "teller":null,
                "title":null
            },
            {
                "id":3,
                "model":"싱클레어",
                "content":"Một thế giới thật hiển nhiên với tôi, không bao giờ thay đổi được. Thế giới của tôi.",
                "place":null,
                "teller":null,
                "title":null
            },
            {
                "id":4,
                "model":"싱클레어",
                "content":"Thế giới ấy bắt đầu trở nên xa lạ vào một ngày…",
                "place":null,
                "teller":null,
                "title":null
            },
            {
                "id":5,
                "model":"싱클레어",
                "content":"Cái ngày mà chị tôi ngồi vào bàn ăn sau khi đã phẩu thuật cấy ghép bộ phận nhân tạo.",
                "place":null,
                "teller":null,
                "title":null
            },
            {
                "id":6,
                "model":"싱클레어",
                "content":"Thế giới của tôi dần thay đổi khi đầu của cha tôi bị thay thế bằng một tổ hộp sắt, cầu chì, và dây dẫn lạ lẫm.",
                "place":null,
                "teller":null,
                "title":null
            },
            {
                "id":7,
                "model":"싱클레어",
                "content":"Những bữa sáng bên gia đình đã không còn là một thế giới ấm áp và tươi sáng nữa. Nó chỉ là một sự kiện khó chịu khi tôi ngày một ít nói lại.",
                "place":null,
                "teller":null,
                "title":null
            },
            {
                "id":8,
                "model":"싱클레어",
                "content":"A… Tôi đã bắt đầu cảm thấy ghê tởm những bộ phận nhân tạo.",
                "place":null,
                "teller":null,
                "title":null
            },
            {
                "id":9,
                "model":"싱클레어",
                "content":"\"Thật dơ bẩn…\"",
                "place":null,
                "teller":null,
                "title":null
            },
            {
                "id":10,
                "model":"싱클레어",
                "content":"Thâm tâm tôi không tài nào chịu nổi cái chấp niệm rằng cơ thể mình nên được thay thế bởi một thứ gì đó khác mà không phải xác thịt và xương cốt.",
                "place":null,
                "teller":null,
                "title":null
            },
            {
                "id":11,
                "model":"싱클레어",
                "content":"Tại sao ta lại dùng cơ thể nhân tạo?",
                "place":null,
                "teller":null,
                "title":null
            },
            {
                "id":12,
                "model":"싱클레어",
                "content":"Tôi thận trọng hỏi lý do, và câu trả lời tôi nhận được rất ngắn gọn và súc tích.",
                "place":null,
                "teller":null,
                "title":null
            },
            {
                "id":13,
                "model":"싱클레어",
                "content":"Cơ thể con người, trong trạng thái chưa được tái tạo, là quá \"lỗi thời\".",
                "place":null,
                "teller":null,
                "title":null
            },
            {
                "id":14,
                "model":"싱클레어",
                "content":"Không ăn thì sẽ đói, không ngủ thì sẽ mệt, bị thương thì mất nhiều thời gian hồi phục.",
                "place":null,
                "teller":null,
                "title":null
            },
            {
                "id":15,
                "model":"싱클레어",
                "content":"Tất cả những điều này khiến cơ thể con người vô cùng kém hiệu quả.",
                "place":null,
                "teller":null,
                "title":null
            },
            {
                "id":16,
                "model":"싱클레어",
                "content":"Ông ấy kết luận rằng cơ thể nhân tạo sẽ ngày càng phát triển theo thời gian, cuối cùng trở thành một phần không thể thiếu trong đời sống thường ngày của chúng ta.",
                "place":null,
                "teller":null,
                "title":null
            },
            {
                "id":17,
                "model":"싱클레어",
                "content":"Tôi thầm nghĩ:",
                "place":null,
                "teller":null,
                "title":null
            },
            {
                "id":18,
                "model":"싱클레어",
                "content":"\"Nếu vậy, thà chặt hết các chi đi còn hơn ấy.\"",
                "place":null,
                "teller":null,
                "title":null
            },
            {
                "id":19,
                "model":"싱클레어",
                "content":"…Dù đó không phải là một lập luận mang tính logic lắm.",
                "place":null,
                "teller":null,
                "title":null
            },
            {
                "id":20,
                "model":"학생크로머",
                "content":"Này, Sinclair… cậu thực sự không muốn làm phẫu thuật cấy ghép đấy đúng chứ?",
                "place":"Lớp Học",
                "teller":"Kromer",
                "title":"Học Sinh"
            },
            {
                "id":21,
                "model":"싱클레어",
                "content":"Tôi gật đầu mà không nói lời nào.",
                "place":null,
                "teller":null,
                "title":null
            },
            {
                "id":22,
                "model":"학생크로머",
                "content":"Nhưng cha mẹ cậu chắc chắn sẽ không vui nếu cậu nói ra điều đấy.",
                "place":null,
                "teller":"Kromer",
                "title":"Học Sinh"
            },
            {
                "id":23,
                "model":"학생크로머",
                "content":"Cậu không cảm thấy bức bối khi bản thân không thể làm bất cứ điều gì sao?",
                "place":null,
                "teller":"Kromer",
                "title":"Học Sinh"
            },
            {
                "id":24,
                "model":"싱클레어",
                "content":"Tôi gật đầu lần nữa.",
                "place":null,
                "teller":null,
                "title":null
            },
            {
                "id":25,
                "model":"학생크로머",
                "content":"Nếu tớ giúp cậu một tay thì sao? Cậu có thể sống một cuộc đời vô lo, không cần phải lo lắng về những chuyện cỏn con ấy nữa.",
                "place":null,
                "teller":"Kromer",
                "title":"Học Sinh"
            },
            {
                "id":26,
                "model":"싱클레어",
                "content":"Nh-Nhưng, làm thế nào?",
                "place":null,
                "teller":null,
                "title":null
            },
            {
                "id":27,
                "model":"학생크로머",
                "content":"Về chuyện đó, cậu sẽ biết sớm thôi.",
                "place":null,
                "teller":"Kromer",
                "title":"Học Sinh"
            },
            {
                "id":28,
                "model":"학생크로머",
                "content":"Đổi lại…",
                "place":null,
                "teller":"Kromer",
                "title":"Học Sinh"
            },
            {
                "id":29,
                "model":"학생크로머",
                "content":"Tớ giúp cậu giải quyết vấn đề, cậu sẽ giải quyết một vài chuyện cá nhân của tớ.",
                "place":null,
                "teller":"Kromer",
                "title":"Học Sinh"
            }
        ]
    }

