
    {
        "dataList":[
            {
                "id":0,
                "place":"Cửu Nhân Hội Trổ Hoa",
                "model":"이스마엘",
                "teller":"Ishmael",
                "title":null,
                "content":"Trông như cả nhóm đang rất yên ổn."
            },
            {
                "id":1,
                "place":null,
                "model":"동랑",
                "teller":"Dongrang",
                "title":"Phòng Ban P.Triển T.Nguyên Thực Phẩm T.Đoàn K",
                "content":"Mọi chuyện đều tốt đẹp trong khoảng thời gian ngắn ngủi đấy. Cứ như chúng tôi đang trên một chuyến dã ngoại vậy. Chúng tôi tưởng mọi thứ sẽ ổn thoả sau khi rời khỏi quê nhà để đến với nơi ở mới, nhưng chao ôi..."
            },
            {
                "id":2,
                "place":null,
                "model":"동랑",
                "teller":"Dongrang",
                "title":"Phòng Ban P.Triển T.Nguyên Thực Phẩm T.Đoàn K",
                "content":"Đến tận cuối cùng thì, xã hội con người cũng không khác biệt nhau là mấy."
            },
            {
                "id":3,
                "place":null,
                "model":"오티스",
                "teller":"Outis",
                "title":null,
                "content":"Hôm nay... tôi để ý thấy thứ gì đó khả nghi ở siêu thị."
            },
            {
                "id":4,
                "place":null,
                "model":"동랑",
                "teller":"Dongrang",
                "title":"Phòng Ban P.Triển T.Nguyên Thực Phẩm T.Đoàn K",
                "content":"Nghe có vẻ thú vị đấy. Nó là gì thế, Sang-heo?"
            },
            {
                "id":5,
                "place":null,
                "model":"오티스",
                "teller":"Outis",
                "title":null,
                "content":"Phát minh này. Không phải là thành quả của cậu khi cậu còn làm việc cho Cửu Nhân Hội sao, Gap-ryong?"
            },
            {
                "id":6,
                "place":null,
                "model":"히스클리프",
                "teller":"Heathcliff",
                "title":null,
                "content":"Đúng... vậy. Nhưng mà, ý tôi là... không cần thiết phải khảo sát thị trường hay gì đó, phải không? Là, là niềm tin và sự tín nhiệm gắn kết chúng ta, nhỉ?"
            },
            {
                "id":7,
                "place":null,
                "model":"오티스",
                "teller":"Outis",
                "title":null,
                "content":"Cậu hẳn đã quên Chín Luật Của Hội rồi."
            },
            {
                "id":8,
                "place":null,
                "model":"료슈",
                "teller":"Ryoshu",
                "title":null,
                "content":"(C.L.C.H. Phì. Thú vị đấy.)"
            },
            {
                "id":9,
                "place":null,
                "model":"싱클레어",
                "teller":"Sinclair",
                "title":null,
                "content":"(Cô Ryōshū! Nếu cô nói những điều không có trong kịch bản thì sẽ gặp rắc rối đấy!)"
            },
            {
                "id":10,
                "place":null,
                "model":"히스클리프",
                "teller":"Heathcliff",
                "title":null,
                "content":"Chậc... tôi biết. Chúng bắt tôi nhớ từng từ một, cậu nghĩ tôi sẽ quên sao?"
            },
            {
                "id":11,
                "place":null,
                "model":"히스클리프",
                "teller":"Heathcliff",
                "title":null,
                "content":"Không một công nghệ nào được tạo ra trong vòng Hội sẽ bị phát tán ra bên ngoài. Phải thật cẩn thận không bị cám dỗ bởi mùi tiền."
            },
            {
                "id":12,
                "place":null,
                "model":"히스클리프",
                "teller":"Heathcliff",
                "title":null,
                "content":"Nhưng... chúng ta được bảo rằng tất cả tài sản sẽ bị thâu tóm nếu không trả tiền thuê phòng thí nghiệm trong vòng sáu ngày tới. Chúng ta phải làm gì đây?"
            },
            {
                "id":13,
                "place":null,
                "model":"히스클리프",
                "teller":"Heathcliff",
                "title":null,
                "content":"Chúng ta phải tìm cách giải quyết chuyện này. Đồng tiền chúng ta nhận được từ nhà máy còn không đủ lót dạ."
            },
            {
                "id":14,
                "place":null,
                "model":"히스클리프",
                "teller":"Heathcliff",
                "title":null,
                "content":"Chúng ta tới từ quận của Tập Đoàn S, chẳng mang theo gì ngoài ngọn lửa đam mê nghiên cứu! Ta biết trả tiền thuê bằng cách nào đây."
            },
            {
                "id":15,
                "place":null,
                "model":"뫼르소",
                "teller":"Meursault",
                "title":null,
                "content":"Nói đúng lắm. Chúng ta phải chịu tiền thuế đắt hơn do đều di cư từ quận khác sang."
            },
            {
                "id":16,
                "place":null,
                "model":"뫼르소",
                "teller":"Meursault",
                "title":null,
                "content":"Họ đang đòi một khoản phí mà chúng ta không có khả năng trả đều đặn hàng tháng."
            },
            {
                "id":17,
                "place":null,
                "model":"이상",
                "teller":"Yi Sang",
                "title":null,
                "content":"...Tôi có thể trả. Nên tôi đề xuất ta bỏ qua vấn đề này đi."
            },
            {
                "id":18,
                "place":null,
                "model":"과거동백",
                "teller":"Dongbaek",
                "title":"Cửu Nhân Hội",
                "content":"Khoan đã, tại sao tôi không được biết bất cứ chuyện này vậy? Tịch thu sao? Anh đã biết trước rồi sao, anh Young-ji? Em muốn nghe trực tiếp chính miệng anh nói hết mọi chuyện ra."
            },
            {
                "id":19,
                "place":null,
                "model":"오티스",
                "teller":"Outis",
                "title":null,
                "content":"Tôi hiểu là cậu giận, nhưng cậu phải nghĩ kỹ về lời nói của mình khi nói với Đàn anh Young-ji đấy Dongbaek."
            },
            {
                "id":20,
                "place":null,
                "model":"홍루",
                "teller":"Hong Lu",
                "title":null,
                "content":"Anh không sao mà, Sang-heo."
            },
            {
                "id":21,
                "place":null,
                "model":"홍루",
                "teller":"Hong Lu",
                "title":null,
                "content":"Dongbaek à, anh định sẽ giải quyết xong việc này rồi mới nói cho em biết. Anh cũng hiểu rằng miễn là chuyện liên quan đến Cửu Nhân Hội, em sẽ là người bất bình đầu tiên."
            },
            {
                "id":22,
                "place":null,
                "model":"홍루",
                "teller":"Hong Lu",
                "title":null,
                "content":"Với lại, Yi Sang ơi. Anh rất cảm kích lời đề nghị này của em, nhưng anh không thể."
            },
            {
                "id":23,
                "place":null,
                "model":"이상",
                "teller":"Yi Sang",
                "title":null,
                "content":"Em không phiền đâu, tích trữ của cải với em là vô nghĩa. Em xin anh hãy dùng nó để chi trả cho Hội."
            },
            {
                "id":24,
                "place":null,
                "model":"이스마엘",
                "teller":"Ishmael",
                "title":null,
                "content":"Gì cơơơ? Ê, Yi Sang! Cậu giàu lên từ khi nào đấy?"
            },
            {
                "id":25,
                "place":null,
                "model":"동랑",
                "teller":"Dongrang",
                "title":"Phòng Ban P.Triển T.Nguyên Thực Phẩm T.Đoàn K",
                "content":"Ha ha, chắc cô phải tập nhớ thoại của mình kỹ hơn chứ nhỉ?"
            },
            {
                "id":26,
                "place":null,
                "model":"동랑",
                "teller":"Dongrang",
                "title":"Phòng Ban P.Triển T.Nguyên Thực Phẩm T.Đoàn K",
                "content":"Kẻ địch sẽ bắt đầu tấn công tiếp đấy, cô biết mà."
            },
            {
                "id":27,
                "place":null,
                "model":"히스클리프",
                "teller":"Heathcliff",
                "title":null,
                "content":"Nhìn xem đứa nào kém tới mức có mấy cái chữ trên giấy đọc còn không xong kìa."
            },
            {
                "id":28,
                "place":null,
                "model":"이스마엘",
                "teller":"Ishmael",
                "title":null,
                "content":"Hà..."
            }
        ]
    }

